.gitignore
MANIFEST.in
README.rst
bootstrap.py
buildout.cfg
collective.captionmanager-configure.zcml
setup.py
collective/__init__.py
collective.captionmanager.egg-info/PKG-INFO
collective.captionmanager.egg-info/SOURCES.txt
collective.captionmanager.egg-info/dependency_links.txt
collective.captionmanager.egg-info/entry_points.txt
collective.captionmanager.egg-info/namespace_packages.txt
collective.captionmanager.egg-info/not-zip-safe
collective.captionmanager.egg-info/requires.txt
collective.captionmanager.egg-info/top_level.txt
collective/captionmanager/__init__.py
collective/captionmanager/configure.zcml
collective/captionmanager/i18n.py
collective/captionmanager/rebuild_i18n.sh
collective/captionmanager/testing.py
collective/captionmanager/upgrades.py
collective/captionmanager/upgrades.zcml
collective/captionmanager/vocabulary.py
collective/captionmanager/browser/__init__.py
collective/captionmanager/browser/captionsfromyoutube_view.py
collective/captionmanager/browser/captionstransformer_view.py
collective/captionmanager/browser/configure.zcml
collective/captionmanager/browser/interfaces.py
collective/captionmanager/locales/collective.captionmanager.pot
collective/captionmanager/locales/en/LC_MESSAGES/collective.captionmanager.po
collective/captionmanager/locales/fr/LC_MESSAGES/collective.captionmanager.po
collective/captionmanager/profiles/default/browserlayer.xml
collective/captionmanager/profiles/default/metadata.xml
collective/captionmanager/tests/__init__.py
collective/captionmanager/tests/base.py
collective/captionmanager/tests/test_setup.py
docs/HISTORY.txt