Metadata-Version: 1.0
Name: collective.captionmanager
Version: 1.0
Summary: Caption manager for Plone
Home-page: https://github.com/collective/collective.captionmanager
Author: JeanMichel FRANCOIS aka toutpt
Author-email: toutpt@gmail.com
License: GPL
Keywords: caption plone
Platform: UNKNOWN
Classifier: Programming Language :: Python
Classifier: Framework :: Plone
Classifier: Framework :: Plone :: 4.0
Classifier: Framework :: Plone :: 4.1
Classifier: Framework :: Plone :: 4.2
